[
  {
    "codigo": "FRITASZONE01_202",
    "estado": "não usado",
    "data_utilizacao": ""
  },
  {
    "codigo": "FRITASZONE01_203",
    "estado": "não usado",
    "data_utilizacao": ""
  },
  {
    "codigo": "FRITASZONE01_204",
    "estado": "não usado",
    "data_utilizacao": ""
  },
  {
    "codigo": "FRITASZONE01_205",
    "estado": "não usado",
    "data_utilizacao": ""
  },
  {
    "codigo": "FRITASZONE01_206",
    "estado": "não usado",
    "data_utilizacao": ""
  },
  {
    "codigo": "FRITASZONE01_207",
    "estado": "não usado",
    "data_utilizacao": ""
  },
  {
    "codigo": "FRITASZONE01_208",
    "estado": "não usado",
    "data_utilizacao": ""
  },
  {
    "codigo": "FRITASZONE01_209",
    "estado": "não usado",
    "data_utilizacao": ""
  },
  {
    "codigo": "FRITASZONE01_2010",
    "estado": "não usado",
    "data_utilizacao": ""
  },
  {
    "codigo": "FRITASZONE01_2011",
    "estado": "não usado",
    "data_utilizacao": ""
  },
  {
    "codigo": "FRITASZONE01_2012",
    "estado": "não usado",
    "data_utilizacao": ""
  },
  {
    "codigo": "FRITASZONE01_2013",
    "estado": "não usado",
    "data_utilizacao": ""
  },
  {
    "codigo": "FRITASZONE01_2014",
    "estado": "não usado",
    "data_utilizacao": ""
  },
  {
    "codigo": "FRITASZONE01_2015",
    "estado": "não usado",
    "data_utilizacao": ""
  },
  {
    "codigo": "FRITASZONE01_2016",
    "estado": "não usado",
    "data_utilizacao": ""
  },
  {
    "codigo": "FRITASZONE01_2017",
    "estado": "não usado",
    "data_utilizacao": ""
  },
  {
    "codigo": "FRITASZONE01_2018",
    "estado": "não usado",
    "data_utilizacao": ""
  },
  {
    "codigo": "FRITASZONE01_2019",
    "estado": "não usado",
    "data_utilizacao": ""
  },
  {
    "codigo": "FRITASZONE01_2020",
    "estado": "não usado",
    "data_utilizacao": ""
  }
]